{"fixtures": [{"id": 257, "code": 2210527, "team_h": 12, "team_h_score": null, "team_a": 17, "team_a_score": null, "event": 26, "finished": false, "minutes": 0, "provisional_start_time": false, "kickoff_time": "2022-02-19T17:30:00Z", "event_name": "Gameweek 26", "is_home": true, "difficulty": 3}, {"id": 266, "code": 2210536, "team_h": 8, "team_h_score": null, "team_a": 12, "team_a_score": null, "event": 27, "finished": false, "minutes": 0, "provisional_start_time": false, "kickoff_time": "2022-02-26T17:30:00Z", "event_name": "Gameweek 27", "is_home": false, "difficulty": 3}, {"id": 275, "code": 2210545, "team_h": 12, "team_h_score": null, "team_a": 13, "team_a_score": null, "event": 28, "finished": false, "minutes": 0, "provisional_start_time": false, "kickoff_time": "2022-03-06T16:30:00Z", "event_name": "Gameweek 28", "is_home": true, "difficulty": 4}, {"id": 285, "code": 2210555, "team_h": 7, "team_h_score": null, "team_a": 12, "team_a_score": null, "event": 29, "finished": false, "minutes": 0, "provisional_start_time": false, "kickoff_time": "2022-03-14T20:00:00Z", "event_name": "Gameweek 29", "is_home": false, "difficulty": 3}, {"id": 295, "code": 2210565, "team_h": 12, "team_h_score": null, "team_a": 4, "team_a_score": null, "event": 30, "finished": false, "minutes": 0, "provisional_start_time": false, "kickoff_time": "2022-03-19T15:00:00Z", "event_name": "Gameweek 30", "is_home": true, "difficulty": 3}, {"id": 302, "code": 2210572, "team_h": 5, "team_h_score": null, "team_a": 12, "team_a_score": null, "event": 31, "finished": false, "minutes": 0, "provisional_start_time": false, "kickoff_time": "2022-04-02T14:00:00Z", "event_name": "Gameweek 31", "is_home": false, "difficulty": 2}, {"id": 316, "code": 2210586, "team_h": 12, "team_h_score": null, "team_a": 11, "team_a_score": null, "event": 32, "finished": false, "minutes": 0, "provisional_start_time": false, "kickoff_time": "2022-04-09T14:00:00Z", "event_name": "Gameweek 32", "is_home": true, "difficulty": 4}, {"id": 330, "code": 2210600, "team_h": 20, "team_h_score": null, "team_a": 12, "team_a_score": null, "event": 33, "finished": false, "minutes": 0, "provisional_start_time": false, "kickoff_time": "2022-04-16T14:00:00Z", "event_name": "Gameweek 33", "is_home": false, "difficulty": 3}, {"id": 339, "code": 2210609, "team_h": 12, "team_h_score": null, "team_a": 18, "team_a_score": null, "event": 34, "finished": false, "minutes": 0, "provisional_start_time": false, "kickoff_time": "2022-04-23T14:00:00Z", "event_name": "Gameweek 34", "is_home": true, "difficulty": 2}, {"id": 343, "code": 2210613, "team_h": 10, "team_h_score": null, "team_a": 12, "team_a_score": null, "event": 35, "finished": false, "minutes": 0, "provisional_start_time": false, "kickoff_time": "2022-04-30T14:00:00Z", "event_name": "Gameweek 35", "is_home": false, "difficulty": 2}, {"id": 359, "code": 2210629, "team_h": 12, "team_h_score": null, "team_a": 14, "team_a_score": null, "event": 36, "finished": false, "minutes": 0, "provisional_start_time": false, "kickoff_time": "2022-05-07T14:00:00Z", "event_name": "Gameweek 36", "is_home": true, "difficulty": 2}, {"id": 369, "code": 2210639, "team_h": 19, "team_h_score": null, "team_a": 12, "team_a_score": null, "event": 37, "finished": false, "minutes": 0, "provisional_start_time": false, "kickoff_time": "2022-05-15T14:00:00Z", "event_name": "Gameweek 37", "is_home": false, "difficulty": 4}, {"id": 379, "code": 2210649, "team_h": 12, "team_h_score": null, "team_a": 2, "team_a_score": null, "event": 38, "finished": false, "minutes": 0, "provisional_start_time": false, "kickoff_time": "2022-05-22T15:00:00Z", "event_name": "Gameweek 38", "is_home": true, "difficulty": 3}], "history": [{"element": 663, "fixture": 185, "opponent_team": 9, "total_points": 0, "was_home": true, "kickoff_time": "2021-12-26T15:00:00Z", "team_h_score": 6, "team_a_score": 3, "round": 19, "minutes": 0, "goals_scored": 0, "assists": 0, "clean_sheets": 0, "goals_conceded": 0, "own_goals": 0, "penalties_saved": 0, "penalties_missed": 0, "yellow_cards": 0, "red_cards": 0, "saves": 0, "bonus": 0, "bps": 0, "influence": "0.0", "creativity": "0.0", "threat": "0.0", "ict_index": "0.0", "value": 50, "transfers_balance": 0, "selected": 0, "transfers_in": 0, "transfers_out": 0}, {"element": 663, "fixture": 192, "opponent_team": 3, "total_points": 0, "was_home": false, "kickoff_time": "2021-12-29T20:15:00Z", "team_h_score": 0, "team_a_score": 1, "round": 20, "minutes": 0, "goals_scored": 0, "assists": 0, "clean_sheets": 0, "goals_conceded": 0, "own_goals": 0, "penalties_saved": 0, "penalties_missed": 0, "yellow_cards": 0, "red_cards": 0, "saves": 0, "bonus": 0, "bps": 0, "influence": "0.0", "creativity": "0.0", "threat": "0.0", "ict_index": "0.0", "value": 50, "transfers_balance": 92, "selected": 189, "transfers_in": 108, "transfers_out": 16}, {"element": 663, "fixture": 201, "opponent_team": 1, "total_points": 0, "was_home": false, "kickoff_time": "2022-01-01T12:30:00Z", "team_h_score": 1, "team_a_score": 2, "round": 21, "minutes": 0, "goals_scored": 0, "assists": 0, "clean_sheets": 0, "goals_conceded": 0, "own_goals": 0, "penalties_saved": 0, "penalties_missed": 0, "yellow_cards": 0, "red_cards": 0, "saves": 0, "bonus": 0, "bps": 0, "influence": "0.0", "creativity": "0.0", "threat": "0.0", "ict_index": "0.0", "value": 50, "transfers_balance": 121, "selected": 329, "transfers_in": 225, "transfers_out": 104}, {"element": 663, "fixture": 215, "opponent_team": 6, "total_points": 0, "was_home": true, "kickoff_time": "2022-01-15T12:30:00Z", "team_h_score": 1, "team_a_score": 0, "round": 22, "minutes": 0, "goals_scored": 0, "assists": 0, "clean_sheets": 0, "goals_conceded": 0, "own_goals": 0, "penalties_saved": 0, "penalties_missed": 0, "yellow_cards": 0, "red_cards": 0, "saves": 0, "bonus": 0, "bps": 0, "influence": "0.0", "creativity": "0.0", "threat": "0.0", "ict_index": "0.0", "value": 50, "transfers_balance": 170, "selected": 698, "transfers_in": 4274, "transfers_out": 4104}, {"element": 663, "fixture": 229, "opponent_team": 16, "total_points": 0, "was_home": false, "kickoff_time": "2022-01-22T17:30:00Z", "team_h_score": 1, "team_a_score": 1, "round": 23, "minutes": 0, "goals_scored": 0, "assists": 0, "clean_sheets": 0, "goals_conceded": 0, "own_goals": 0, "penalties_saved": 0, "penalties_missed": 0, "yellow_cards": 0, "red_cards": 0, "saves": 0, "bonus": 0, "bps": 0, "influence": "0.0", "creativity": "0.0", "threat": "0.0", "ict_index": "0.0", "value": 50, "transfers_balance": 10, "selected": 753, "transfers_in": 16725, "transfers_out": 16715}, {"element": 663, "fixture": 238, "opponent_team": 3, "total_points": 0, "was_home": true, "kickoff_time": "2022-02-09T19:45:00Z", "team_h_score": 2, "team_a_score": 0, "round": 24, "minutes": 0, "goals_scored": 0, "assists": 0, "clean_sheets": 0, "goals_conceded": 0, "own_goals": 0, "penalties_saved": 0, "penalties_missed": 0, "yellow_cards": 0, "red_cards": 0, "saves": 0, "bonus": 0, "bps": 0, "influence": "0.0", "creativity": "0.0", "threat": "0.0", "ict_index": "0.0", "value": 50, "transfers_balance": 291, "selected": 1229, "transfers_in": 495, "transfers_out": 204}, {"element": 663, "fixture": 248, "opponent_team": 15, "total_points": 1, "was_home": false, "kickoff_time": "2022-02-12T17:30:00Z", "team_h_score": 0, "team_a_score": 4, "round": 25, "minutes": 6, "goals_scored": 0, "assists": 0, "clean_sheets": 0, "goals_conceded": 0, "own_goals": 0, "penalties_saved": 0, "penalties_missed": 0, "yellow_cards": 0, "red_cards": 0, "saves": 0, "bonus": 0, "bps": 2, "influence": "0.0", "creativity": "0.3", "threat": "0.0", "ict_index": "0.0", "value": 50, "transfers_balance": 65, "selected": 1335, "transfers_in": 220, "transfers_out": 155}], "history_past": []}